encrypt_data/__init__.py
encrypt_data/main.py
encrypt_data-0.4.dist-info/METADATA
encrypt_data-0.4.dist-info/WHEEL
encrypt_data-0.4.dist-info/top_level.txt
encrypt_data-0.4.dist-info/RECORD
