Metadata-Version: 2.2
Name: encrypt_data
Version: 0.4
Summary: Hybrid Encryption & Decryption with Minimal Efforts.
Home-page: https://github.com/Manthan-04/encrypt_data.git
Author: Manthan Phadse
Author-email: manthan.phadse04@gmail.com
Classifier: Programming Language :: Python :: 3
Classifier: License :: OSI Approved :: MIT License
Classifier: Operating System :: OS Independent
Requires-Python: >=3.6
Requires-Dist: cryptography
Requires-Dist: rsa
Dynamic: author
Dynamic: author-email
Dynamic: classifier
Dynamic: description
Dynamic: description-content-type
Dynamic: home-page
Dynamic: requires-dist
Dynamic: requires-python
Dynamic: summary
